tansy/__init__.py
tansy/class_slash.py
tansy/slash_commands.py
tansy/slash_param.py
tansy/utils.py
tansy-0.10.0.dist-info/licenses/LICENSE
tansy-0.10.0.dist-info/METADATA
tansy-0.10.0.dist-info/WHEEL
tansy-0.10.0.dist-info/top_level.txt
tansy-0.10.0.dist-info/RECORD
