Metadata-Version: 2.4
Name: tansy
Version: 0.10.0
Summary: Unstable experiments with interactions.py.
Home-page: https://github.com/Astrea-Stellarium-Labs/tansy
Author: AstreaTSS
Classifier: Programming Language :: Python :: 3
Classifier: License :: OSI Approved :: MIT License
Classifier: Operating System :: OS Independent
Requires-Python: >=3.10
License-File: LICENSE
Requires-Dist: discord-py-interactions>=5.15.0
Dynamic: author
Dynamic: classifier
Dynamic: description
Dynamic: description-content-type
Dynamic: home-page
Dynamic: license-file
Dynamic: requires-dist
Dynamic: requires-python
Dynamic: summary
